{
  "complete": false,
  "content_hash": "ccf2f36754c2755b24a5dcb709e34be6bc07cb211f6b151b1d288145b91b2dd0",
  "data": {
    "changed": true,
    "duration_ms": 9909,
    "items": {
      "direct": {
        "changed": false,
        "complete": true,
        "content_hash": "47ebbb636d830e3f6c00425aaeb88008d532c227a47ebee65c246916b4918986",
        "preserved": false,
        "status": "complete"
      },
      "exhibition": {
        "changed": false,
        "complete": true,
        "content_hash": "6c1ecc75988454858e4d333525cc1d2582f014cfa9923481bb332e0d71a23c3b",
        "preserved": false,
        "status": "complete"
      },
      "odds": {
        "changed": false,
        "complete": false,
        "content_hash": "e72a54d6a9a81b11d0939be8e892450240e54542fd3fd753e54e3c6be1c50fcc",
        "preserved": false,
        "status": "partial"
      },
      "original_exhibition": {
        "changed": true,
        "complete": true,
        "content_hash": "0f5fd276f0b38d654bc7327c00edae46ce1e350b48965e4cb5e96ee89b80a052",
        "preserved": false,
        "status": "complete"
      }
    }
  },
  "date": "2026-07-24",
  "deadline": "12:44",
  "error": null,
  "fetched_at": "2026-07-24T12:43:32+09:00",
  "race_no": 5,
  "source": "https://boaters-boatrace.com",
  "status": "partial",
  "venue": "toda"
}
