{
  "complete": true,
  "content_hash": "8bc9c4edd37ed205f16abf513c1caa6a4abc41b8a1516b584c500c5d3e7876ff",
  "data": {
    "full_order": [],
    "kimarite": "",
    "order": [
      "2",
      "1",
      "3"
    ],
    "payout3t": "890円",
    "popularity3t": 2
  },
  "date": "2026-07-24",
  "deadline": "15:30",
  "error": null,
  "fetched_at": "2026-07-24T15:37:36+09:00",
  "race_no": 1,
  "source": "https://www.boatrace.jp/owpc/pc/race/raceresult?rno=1&jcd=19&hd=20260724",
  "status": "complete",
  "venue": "shimonoseki"
}
