{
  "complete": true,
  "content_hash": "63fcd116d74fd1be6a081fbd77771523adccbe129f580d02bd244aa3bcf25153",
  "data": {
    "entries": [
      {
        "exhibition_course": 1,
        "exhibition_rank": 2,
        "exhibition_time": 6.76,
        "lane": 1,
        "name": "土屋 南",
        "player_id": 4964,
        "start_rank": 1,
        "start_raw": 0.11,
        "start_time": 0.11,
        "tilt": 0
      },
      {
        "exhibition_course": 2,
        "exhibition_rank": 1,
        "exhibition_time": 6.74,
        "lane": 2,
        "name": "原村 百那",
        "player_id": 5342,
        "start_rank": 4,
        "start_raw": 0.38,
        "start_time": 0.38,
        "tilt": 0
      },
      {
        "exhibition_course": 3,
        "exhibition_rank": 4,
        "exhibition_time": 6.8,
        "lane": 3,
        "name": "島倉 都",
        "player_id": 4987,
        "start_rank": 1,
        "start_raw": 0.11,
        "start_time": 0.11,
        "tilt": 0
      },
      {
        "exhibition_course": 4,
        "exhibition_rank": 6,
        "exhibition_time": 6.83,
        "lane": 4,
        "name": "赤澤 文香",
        "player_id": 4098,
        "start_rank": 5,
        "start_raw": 0.4,
        "start_time": 0.4,
        "tilt": -0.5
      },
      {
        "exhibition_course": 5,
        "exhibition_rank": 4,
        "exhibition_time": 6.8,
        "lane": 5,
        "name": "出穂 和鼓",
        "player_id": 5391,
        "start_rank": 5,
        "start_raw": 0.4,
        "start_time": 0.4,
        "tilt": 0
      },
      {
        "exhibition_course": 6,
        "exhibition_rank": 3,
        "exhibition_time": 6.79,
        "lane": 6,
        "name": "宮城 那菜",
        "player_id": 5413,
        "start_rank": 3,
        "start_raw": 0.25,
        "start_time": 0.25,
        "tilt": 0
      }
    ],
    "slit_source": [
      {
        "course": 1,
        "lane": 1,
        "start_raw": 0.11,
        "start_time": 0.11
      },
      {
        "course": 2,
        "lane": 2,
        "start_raw": 0.38,
        "start_time": 0.38
      },
      {
        "course": 3,
        "lane": 3,
        "start_raw": 0.11,
        "start_time": 0.11
      },
      {
        "course": 4,
        "lane": 4,
        "start_raw": 0.4,
        "start_time": 0.4
      },
      {
        "course": 5,
        "lane": 5,
        "start_raw": 0.4,
        "start_time": 0.4
      },
      {
        "course": 6,
        "lane": 6,
        "start_raw": 0.25,
        "start_time": 0.25
      }
    ],
    "start_order": [
      1,
      3,
      6,
      2,
      4,
      5
    ]
  },
  "date": "2026-07-24",
  "deadline": "18:54",
  "error": null,
  "fetched_at": "2026-07-24T18:43:44+09:00",
  "race_no": 8,
  "source": "https://boaters-boatrace.com/race/shimonoseki/2026-07-24/8R/last-minute",
  "status": "complete",
  "venue": "shimonoseki"
}
