{
  "complete": false,
  "content_hash": "364a8916bdcdbc67ae2791ffbce7a4b3fa5ff98d2e0409fda032f7b50daab77a",
  "data": {
    "changed": true,
    "duration_ms": 14803,
    "items": {
      "direct": {
        "changed": true,
        "complete": false,
        "content_hash": "4c9ca5cac831d2becb7ead119b80574e623fad5e1077c652180e8d0d1cfc2a76",
        "preserved": false,
        "status": "pending"
      },
      "exhibition": {
        "changed": true,
        "complete": false,
        "content_hash": "5e357629da7545ed6add282820cc55deead8932443cbb36839eee8eafeda94d9",
        "preserved": false,
        "status": "pending"
      },
      "odds": {
        "changed": true,
        "complete": true,
        "content_hash": "8479149905bdab214edd5d0e26de6aa9ffe878a9ace0158396a92a61cbf6872c",
        "preserved": false,
        "status": "complete"
      },
      "original_exhibition": {
        "changed": true,
        "complete": false,
        "content_hash": "3b9b5167e65c210722acd651418366f99bb02dff12a50f61802c6093bcaa1625",
        "preserved": false,
        "status": "pending"
      }
    }
  },
  "date": "2026-07-24",
  "deadline": "16:06",
  "error": null,
  "fetched_at": "2026-07-24T15:23:03+09:00",
  "race_no": 12,
  "source": "https://boaters-boatrace.com",
  "status": "partial",
  "venue": "tokoname"
}
