{
  "complete": true,
  "content_hash": "804066256b6099115cff8b1d11dee1ecc0d6cffbc23e6a2528a255edc2c6fff7",
  "data": {
    "entries": [
      {
        "lane": 1,
        "lap_time": 37.52,
        "name": "桐本 康臣",
        "player_id": 4043,
        "straight_time": 6.96,
        "turn_time": 5.56
      },
      {
        "lane": 2,
        "lap_time": 37.89,
        "name": "福嶋 智之",
        "player_id": 4054,
        "straight_time": 7.17,
        "turn_time": 5.73
      },
      {
        "lane": 3,
        "lap_time": 37.64,
        "name": "原田 秀弥",
        "player_id": 3963,
        "straight_time": 7.28,
        "turn_time": 5.6
      },
      {
        "lane": 4,
        "lap_time": 37.73,
        "name": "片岡 大地",
        "player_id": 4911,
        "straight_time": 7.08,
        "turn_time": 5.63
      },
      {
        "lane": 5,
        "lap_time": 38.2,
        "name": "鈴木 裕隆",
        "player_id": 4231,
        "straight_time": 7.13,
        "turn_time": 5.74
      },
      {
        "lane": 6,
        "lap_time": 38.4,
        "name": "山下 拓巳",
        "player_id": 5273,
        "straight_time": 7.13,
        "turn_time": 5.61
      }
    ],
    "tab_clicked": true
  },
  "date": "2026-07-24",
  "deadline": "14:48",
  "error": null,
  "fetched_at": "2026-07-24T14:48:41+09:00",
  "race_no": 9,
  "source": "https://boaters-boatrace.com/race/toda/2026-07-24/9R/last-minute",
  "status": "complete",
  "venue": "toda"
}
